mantisconnect2/__init__.py
mantisconnect2/connector.py
mantisconnect2/connector_interface.py
mantisconnect2/connector_v1.py
mantisconnect2/connector_v2.py
mantisconnect2/project.py
mantisconnect2/simple_project.py
mantisconnect2-0.4.1.dist-info/LICENSE.txt
mantisconnect2-0.4.1.dist-info/METADATA
mantisconnect2-0.4.1.dist-info/WHEEL
mantisconnect2-0.4.1.dist-info/top_level.txt
mantisconnect2-0.4.1.dist-info/RECORD
