Metadata-Version: 2.1
Name: mantisconnect2
Version: 0.4.1
Summary: Python client for Mantis connect SOAP API
Home-page: https://github.com/tigerking/mantisconnect2
Author: Ji Haijun
Author-email: tigerking1218@gmail.com
License: MIT
Platform: UNKNOWN
Classifier: Programming Language :: Python
Classifier: Programming Language :: Python :: 2.7
Classifier: Programming Language :: Python :: 3.4
Classifier: Programming Language :: Python :: 3.5
Classifier: Programming Language :: Python :: 3.6
Classifier: Programming Language :: Python :: 3.7
Classifier: Topic :: Software Development :: Libraries :: Python Modules
Classifier: Topic :: Utilities
